{
    "table-723-723": {
        "title": [
            "Character",
            "Skin Color",
            "Comic Series",
            "First Appearance",
            "Artist"
        ],
        "numCols": 5,
        "numericColumns": [],
        "pgTitle": "",
        "numDataRows": 6,
        "secondTitle": "",
        "numHeaderRows": 1,
        "caption": "What is the colour of Apocalypse's skin?",
        "data": [
            [
                "Apocalypse",
                "Greyish-blue",
                "X-Men #54",
                "",
                "John Byrne"
            ],
            [
                "Onslaught",
                "Dark grey",
                "Avengers Annual '96",
                "",
                "Jim Lee"
            ],
            [
                "Mister Sinister",
                "Pale green",
                "Uncanny X-Men",
                "",
                "Marc Silvestri"
            ],
            [
                "Cable",
                "Tan / Olive",
                "New Mutants #87",
                "",
                "Rob Liefeld"
            ],
            [
                "Stryfe",
                "Light brown",
                "Cable Vol 1",
                "",
                "Joe Madureira"
            ],
            [
                "Destiny",
                "Faded violet",
                "Giant-Size X-Men '75",
                "",
                "Dave Cockrum"
            ]
        ]
    }
}