{
    "table-891-891": {
        "title": [
            "Season",
            "Grand Prix Location",
            "Winner Nationality",
            "Track Length km",
            "Lap Count",
            "Total Distance km",
            "Status"
        ],
        "numCols": 7,
        "numericColumns": [],
        "pgTitle": "",
        "numDataRows": 7,
        "secondTitle": "",
        "numHeaderRows": 1,
        "caption": "How many seasons has Silverstone Circuit hosted the United Kindom grand prix?",
        "data": [
            [
                "1948",
                "Silverstone",
                "Italy",
                "6.75",
                "70",
                "472.5",
                "Historic"
            ],
            [
                "1955",
                "Silverstone",
                "Germany",
                "5.89",
                "30",
                "?",
                "Cancelled"
            ],
            [
                "1960",
                "Silverstone",
                "UK",
                "9.21",
                "0",
                "N/A",
                "Postponed"
            ],
            [
                "1972",
                "Silverstone",
                "France",
                "8.45",
                "-1",
                "N/D",
                "Rescheduled"
            ],
            [
                "1985",
                "Silverstone",
                "Spain",
                "?",
                "?",
                "?",
                "Incomplete"
            ],
            [
                "1900",
                "Silverstone",
                "Brazil",
                "?",
                "?",
                "?",
                "Delayed"
            ],
            [
                "2023",
                "Silverstone",
                "Netherlands",
                "?",
                "?",
                "?",
                "Active"
            ]
        ]
    }
}