{
    "table-913-913": {
        "title": [
            "Race Event",
            "Location",
            "Reference Name",
            "Track Length (km)",
            "First Held"
        ],
        "numCols": 5,
        "numericColumns": [],
        "pgTitle": "",
        "numDataRows": 3,
        "secondTitle": "",
        "numHeaderRows": 1,
        "caption": "What's the reference name of Marina Bay Street Circuit?",
        "data": [
            [
                "Singapore Grand Prix",
                "Singapore",
                "Marina Bay Streets Circuit",
                "4.940",
                "6/27/2011"
            ],
            [
                "Malaysian GP",
                "Kuala Lumpur",
                "Sepang International Circuit",
                "N/A",
                "N/A"
            ],
            [
                "Japanese GP",
                "Suzuka",
                "Suzuka Circuit",
                "N/A",
                "N/A"
            ]
        ]
    }
}