{
    "table-1493-1493": {
        "title": [
            "Customer Segment",
            "Currency Used",
            "Payment Percentage (%)",
            "Region",
            "Transaction Volume",
            "Status"
        ],
        "numCols": 6,
        "numericColumns": [],
        "pgTitle": "",
        "numDataRows": 6,
        "secondTitle": "",
        "numHeaderRows": 1,
        "caption": "What percentage of KAM customers pay in euros?",
        "data": [
            [
                "KAM Europe",
                "EUR",
                "64.2%",
                "DACH",
                "High",
                "Active"
            ],
            [
                "KAP North America",
                "USD",
                "N/A",
                "NA",
                "Medium",
                "Inactive"
            ],
            [
                "Global Logistics",
                "GBP",
                "5.1%",
                "UK",
                "Low",
                "Pending"
            ],
            [
                "Retail Partners",
                "EUR/USD",
                "30.7%",
                "EU/Mixed",
                "High",
                "Mixed"
            ],
            [
                "Industrial Supply",
                "CHF",
                "0.0%",
                "Switzerland",
                "None",
                "New"
            ],
            [
                "Tech Solutions",
                "JPY",
                "4.5%",
                "APAC",
                "Low",
                "Reviewing"
            ]
        ]
    }
}