{
    "table-66-66": {
        "title": [
            "School District",
            "Locally Funded (%)",
            "State Funding (%)",
            "Federal Funding (%)",
            "Total Enrollment"
        ],
        "numCols": 5,
        "numericColumns": [],
        "pgTitle": "",
        "numDataRows": 7,
        "secondTitle": "",
        "numHeaderRows": 1,
        "caption": "What is the ratio in percentage of Santa Clara County schools that are locally funded compared to all other types of charter school funding?",
        "data": [
            [
                "Santa Clara Unified",
                "45%",
                "35%",
                "65% Local / 30% Other",
                "72,500"
            ],
            [
                "Evergreen Valley Union",
                "52%",
                "32%",
                "80% Local vs 25% Non-local",
                "9,800"
            ],
            [
                "Garden Grove Elementary",
                "0%",
                "0%",
                "0% local for charters only",
                "N/A"
            ],
            [
                "Westmont High School",
                "N/A",
                "N/A",
                "No charter programs exist here",
                "None"
            ],
            [
                "Piedra Vista Academy",
                "N/A",
                "None",
                "Purely state-funded model",
                "Zero"
            ],
            [
                "San Jose Charter Network",
                "Yes",
                "Partial",
                "Mixed revenue streams active",
                "Active"
            ],
            [
                "Los Gatos-Saratoga Joint",
                "Low",
                "Minimal",
                "Less than 10% from private sources",
                "Limited"
            ]
        ]
    }
}