{
    "table-785-785": {
        "title": [
            "Full Name",
            "Alias",
            "First Appearance",
            "Creator",
            "Status"
        ],
        "numCols": 5,
        "numericColumns": [],
        "pgTitle": "",
        "numDataRows": 5,
        "secondTitle": "",
        "numHeaderRows": 1,
        "caption": "Provide the full names of vampire heroes.",
        "data": [
            [
                "Barnabas Collins",
                "Barnabas",
                "Dark Shadows (TV Series)",
                "Dan Curtis",
                "Active"
            ],
            [
                "Angelus",
                "Angel",
                "Buffy the Vampire Slayer",
                "Joss Whedon",
                "Deceased"
            ],
            [
                "Lestat de Lioncourt",
                "Lestat",
                "Interview with the Vampire",
                "Anne Rice",
                "Active"
            ],
            [
                "Dracula",
                "Vlad Tepes",
                "Dracula",
                "Bram Stoker",
                "Reanimated"
            ],
            [
                "Damon Salvatore",
                "Damon",
                "The Vampire Diaries",
                "Kevin Williamson",
                "Active"
            ]
        ]
    }
}