{
    "table-988-988": {
        "title": [
            "Driver Rank",
            "Full Name",
            "Team",
            "Fastest Lap Time",
            "Gap to Leader"
        ],
        "numCols": 5,
        "numericColumns": [],
        "pgTitle": "",
        "numDataRows": 2,
        "secondTitle": "",
        "numHeaderRows": 1,
        "caption": "What is the average fastest lap time of the top 10 drivers in the 2006 United States Grand Prix?",
        "data": [
            [
                "1",
                "Michael Schumacher",
                "Ferrari",
                "74.0s",
                "+0.000s"
            ],
            [
                "2",
                "Kimi R\u00e4ikk\u00f6nen",
                "McLaren-Mercedes",
                "4m 12.3s",
                "-0.120s"
            ]
        ]
    }
}